ubipod/__init__.py
ubipod/binary.py
ubipod/circuit.py
ubipod/common.py
ubipod/ghost.py
ubipod/images.py
ubipod/object.py
ubipod/pbdf.py
ubipod/py.typed
ubipod/scripts.py
ubipod/sounds.py
ubipod/texture.py
ubipod/typing.py
ubipod/vehicle.py
ubipod-0.6.1.dist-info/METADATA
ubipod-0.6.1.dist-info/WHEEL
ubipod-0.6.1.dist-info/licenses/LICENSE
ubipod-0.6.1.dist-info/RECORD
