Metadata-Version: 2.4
Name: ubipod
Version: 0.6.1
Summary: Loads and saves UbiSoft Pod file formats
Project-URL: Repository, https://gitlab.com/Syroot/Pod/ubipod
Project-URL: Issues, https://gitlab.com/Syroot/Pod/ubipod/-/issues
Author-email: Syroot <dev@syroot.com>
License-Expression: GPL-3.0-or-later
License-File: LICENSE
Classifier: Operating System :: OS Independent
Classifier: Programming Language :: Python :: 3
Classifier: Topic :: File Formats
Classifier: Topic :: Games/Entertainment
Requires-Python: >=3.11
